contact_magic/__init__.py
contact_magic/asyncio.py
contact_magic/callbacks.py
contact_magic/conf/__init__.py
contact_magic/conf/all_technology_categories.py
contact_magic/conf/settings.py
contact_magic/dict_utils.py
contact_magic/helpers.py
contact_magic/integrations/__init__.py
contact_magic/integrations/copyfactory.py
contact_magic/integrations/sales_scrapers.py
contact_magic/integrations/sheets.py
contact_magic/logger.py
contact_magic/models.py
contact_magic/preprocessors.py
contact_magic/scripts/__init__.py
contact_magic/scripts/agency.py
contact_magic/scripts/default_scraper_options.py
contact_magic/scripts/logger.py
contact_magic/scripts/run_workflows.py
contact_magic/scripts/sync_scraper_options_to_workersheets.py
contact_magic/scripts/update_workflow_approval_metrics.py
contact_magic/utils.py
contact_magic-0.9.4.dist-info/METADATA
contact_magic-0.9.4.dist-info/WHEEL
contact_magic-0.9.4.dist-info/entry_points.txt
contact_magic-0.9.4.dist-info/RECORD
