Metadata-Version: 2.1
Name: contact-magic
Version: 0.9.4
Summary: Quickly set up workflows for retrieving hard-to-find contact information and composing personalized messages based on any data point.
License: MIT
Author: Copyfactory
Author-email: dev@copyfactory.io
Requires-Python: >=3.10,<4.0
Classifier: Development Status :: 4 - Beta
Classifier: Environment :: Web Environment
Classifier: Intended Audience :: Developers
Classifier: Intended Audience :: Information Technology
Classifier: Intended Audience :: System Administrators
Classifier: License :: OSI Approved :: MIT License
Classifier: Operating System :: OS Independent
Classifier: Programming Language :: Python
Classifier: Programming Language :: Python :: 3
Classifier: Programming Language :: Python :: 3.10
Classifier: Programming Language :: Python :: 3.11
Classifier: Programming Language :: Python :: 3 :: Only
Classifier: Programming Language :: Python :: 3.7
Classifier: Programming Language :: Python :: 3.8
Classifier: Programming Language :: Python :: 3.9
Classifier: Topic :: Internet
Classifier: Topic :: Software Development
Classifier: Topic :: Software Development :: Libraries
Classifier: Topic :: Software Development :: Libraries :: Python Modules
Classifier: Typing :: Typed
Provides-Extra: sheets
Requires-Dist: gspread (==4.0.1) ; extra == "sheets"
Requires-Dist: httpx (>=0.24.1,<0.25.0)
Requires-Dist: oauth2client (==4.1.3) ; extra == "sheets"
Requires-Dist: oauthlib (==3.1.1) ; extra == "sheets"
Requires-Dist: pandas (>=2.0.2,<3.0.0)
Requires-Dist: pydantic (==1.10.8)
Requires-Dist: python-dotenv (>=1.0.0,<2.0.0)
Requires-Dist: rich (>=13.4.1,<14.0.0)
Requires-Dist: structlog (==23.1.0)
Requires-Dist: typer[all] (>=0.9.0,<0.10.0)
